presalytics_ooxml_automation/__init__.py
presalytics_ooxml_automation/api_client.py
presalytics_ooxml_automation/configuration.py
presalytics_ooxml_automation/exceptions.py
presalytics_ooxml_automation/rest.py
presalytics_ooxml_automation/api/__init__.py
presalytics_ooxml_automation/api/default_api.py
presalytics_ooxml_automation/models/__init__.py
presalytics_ooxml_automation/models/chart_axes.py
presalytics_ooxml_automation/models/chart_axes_details.py
presalytics_ooxml_automation/models/chart_axis_data_types.py
presalytics_ooxml_automation/models/chart_chart_data.py
presalytics_ooxml_automation/models/chart_chart_data_details.py
presalytics_ooxml_automation/models/chart_charts.py
presalytics_ooxml_automation/models/chart_charts_details.py
presalytics_ooxml_automation/models/chart_column_collections.py
presalytics_ooxml_automation/models/chart_column_collections_details.py
presalytics_ooxml_automation/models/chart_columns.py
presalytics_ooxml_automation/models/chart_columns_details.py
presalytics_ooxml_automation/models/chart_data_points.py
presalytics_ooxml_automation/models/chart_data_points_details.py
presalytics_ooxml_automation/models/chart_plot_type.py
presalytics_ooxml_automation/models/chart_row_col.py
presalytics_ooxml_automation/models/chart_row_collections.py
presalytics_ooxml_automation/models/chart_row_collections_details.py
presalytics_ooxml_automation/models/chart_row_name_format_types.py
presalytics_ooxml_automation/models/chart_rows.py
presalytics_ooxml_automation/models/chart_rows_details.py
presalytics_ooxml_automation/models/child_objects.py
presalytics_ooxml_automation/models/document.py
presalytics_ooxml_automation/models/document_details.py
presalytics_ooxml_automation/models/document_type.py
presalytics_ooxml_automation/models/ooxml_dto.py
presalytics_ooxml_automation/models/problem_details.py
presalytics_ooxml_automation/models/shared_color_transformation_attributes.py
presalytics_ooxml_automation-0.2.54.dist-info/LICENSE
presalytics_ooxml_automation-0.2.54.dist-info/METADATA
presalytics_ooxml_automation-0.2.54.dist-info/WHEEL
presalytics_ooxml_automation-0.2.54.dist-info/top_level.txt
presalytics_ooxml_automation-0.2.54.dist-info/RECORD
