Metadata-Version: 2.1
Name: presalytics-ooxml-automation
Version: 0.2.54
Summary: OOXML Automation
Home-page: https://github.com/presalytics/ooxml-automation-python-client
Author-email: kevin@presalytics.io
License: UNKNOWN
Keywords: OpenAPI,OpenAPI-Generator,OOXML Automation
Platform: UNKNOWN
Requires-Dist: urllib3 (>=1.15)
Requires-Dist: six (>=1.10)
Requires-Dist: certifi
Requires-Dist: python-dateutil
